de_test_1.py
de_test_1-0.2.dist-info/WHEEL
de_test_1-0.2.dist-info/METADATA
de_test_1-0.2.dist-info/RECORD
