Metadata-Version: 2.1
Name: de_test_1
Version: 0.2
Summary: Sample package!
Author-email: Derek Evans <derek.evans@deinfoservice.com>
Project-URL: Homepage, https://www.techbyderek.com
